mysql2s3/__init__.py
mysql2s3/mysql2s3.py
mysql2s3/verify_dump.py
mysql2s3-0.1.0.dist-info/entry_points.txt
mysql2s3-0.1.0.dist-info/WHEEL
mysql2s3-0.1.0.dist-info/METADATA
mysql2s3-0.1.0.dist-info/RECORD
